{
  "chain_name": "xos",
  "status": "live",
  "network_type": "testnet",
  "pretty_name": "XOS Testnet",
  "chain_id": "xos-testnet-1",
  "bech32_prefix": "xos",
  "rpc": [
    "https://testnet-rpc.x.ink",
    "https://testnet-rpc.xoscan.io"
  ],
  "api": [],
  "logo": "https://raw.githubusercontent.com/maouamnodelab/logos/refs/heads/main/xos.jpg"

  "stake_currency": {
    "coin_denom": "XOS",
    "coin_minimal_denom": "XOS",
    "coin_decimals": 6
  },
  "currencies": [
    {
      "coin_denom": "XOS",
      "coin_minimal_denom": "XOS",
      "coin_decimals": 6
    }
  ]
}
